buvar/config.py
buvar/log.py
buvar/util.py
buvar/fork.py
buvar/__init__.py
buvar/context.py
buvar/plugin.py
buvar/testing.py
buvar/di/c_di.pyx
buvar/di/__init__.py
buvar/di/c_di.cpython-312-darwin.so
buvar/di/exc.py
buvar/di/py_di.py
buvar/plugins/bg.py
buvar/plugins/__init__.py
buvar/components/py_components.py
buvar/components/__init__.py
buvar/components/c_components.cpython-312-darwin.so
buvar/components/c_components.pyx
buvar-0.44.16.dist-info/RECORD
buvar-0.44.16.dist-info/WHEEL
buvar-0.44.16.dist-info/entry_points.txt
buvar-0.44.16.dist-info/top_level.txt
buvar-0.44.16.dist-info/METADATA
buvar-0.44.16.dist-info/licenses/LICENSE-APACHE
buvar-0.44.16.dist-info/licenses/LICENSE-MIT
