Metadata-Version: 2.4
Name: buvar
Version: 0.44.16
Summary: Asyncio plugins, components, dependency injection and configs
Requires-Python: >=3.11
License-File: LICENSE-APACHE
License-File: LICENSE-MIT
Requires-Dist: attrs
Requires-Dist: cattrs
Requires-Dist: structlog>=20.1.0
Requires-Dist: toml>=0.10
Requires-Dist: typing_inspect>=0.4.0
Requires-Dist: cached_property
Requires-Dist: uritools
Dynamic: license-file
